{
  "image": {},
  "src": null,
  "_stats": {
    "modifiedTime": 1689702563173,
    "systemId": "cyphersystem",
    "lastModifiedBy": "EcFzQPPYnESXtTnB",
    "createdTime": null,
    "systemVersion": "2.8.2",
    "coreVersion": "11.305"
  },
  "flags": {},
  "sort": 387500,
  "video": {
    "volume": 0.5,
    "controls": true
  },
  "type": "text",
  "title": {
    "level": 1,
    "show": true
  },
  "system": {},
  "ownership": {
    "default": -1
  },
  "name": "Aspectos",
  "_id": "gUBd9dvLJ8qY0iZx",
  "text": {
    "format": 1,
    "markdown": "",
    "content": "<p>Los aspectos son conjuntos de capacidades especiales que el DJ y los jugadores pueden utilizar para alterar un tipo de personaje y hacerlo más a su gusto o más apropiado para el género o la ambientación. Por ejemplo, si un jugador quiere crear un personaje ladrón que utilice la magia, podría jugar con un Adepto con aspecto de sigilo. En una ambientación de ciencia ficción, un Guerrero también podría tener conocimientos de maquinaria, por lo que el personaje podría tener aspecto de tecnología.</p><p>Para cada rango de personaje determinado, las capacidades provistas por un aspecto se pueden intercambiar a razón de uno a uno con las capacidades estándar de tipo. Así que para añadir la capacidad del aspecto Sentido del peligro a un Guerrero, hay que sacrificar otra cosa -quizás Golpe-. Ahora, ese personaje puede elegir Sentido del peligro como lo haría con cualquier otra habilidad de Guerrero de primer rango, pero nunca podrá elegir Golpe.</p><p>l DJ siempre debe participar en la aplicación de aspectos a los tipo. Por ejemplo, puede saber que para su juego de ciencia ficción quiere un tipo llamado \"Glam\", que es un Orador con ciertas habilidades tecnológicas -especialmente las que convierten al personaje en un extravagante piloto de naves estelares-. Por lo tanto, cambia las habilidades de primer nivel Giro de identidad e Inspirar agresividad por las capacidades de aspecto tecnológico Datajack y Habilidades técnicas para que el personaje pueda conectarse directamente a la nave y pueda tomar el pilotaje y las computadoras como habilidades.</p><p>Al final, los aspectos son sobre todo herramientas para que el DJ pueda crear fácilmente tipos específicos para la campaña haciendo unas ligeras alteraciones a los cuatro tipos base. Aunque los jugadores pueden desear utilizar los aspectos para conseguir los personajes que desean, recuerda que también pueden dar forma a sus PJ con descriptores y rasgos de forma muy efectiva.</p><p>Los aspectos disponibles son: Sigilo, Tecnología, Magia, Combate, y Habilidades y Conocimientos.</p><p>La descripción completa de cada capacidad listada se encuentra en el capítulo de Capacidades, que también contiene descripciones de capacidades de tipo y de rasgo en un amplio catálogo unificado.</p><h1>Aspecto de Sigilo</h1><p>Los personajes con el aspecto de sigilo son buenos para escabullirse, infiltrarse en lugares de difícil acceso y engañar a los demás. Utilizan estas capacidades de diversas maneras, incluyendo el combate. Un Explorador con aspecto de sigilo podría ser un ladrón, mientras que un Guerrero con aspecto de sigilo podría ser un asesino. Un Explorador con aspecto de sigilo en una ambientación de superhéroes podría ser un luchador contra el crimen que acecha las calles por la noche.</p><h3>Capacidades de Sigilo de Primer Rango</h3><p>@UUID[Compendium.drsc-es-compendio-foundry.abilities.UyQTRi5ZwWU5tMO0]{Sentido del peligro} @UUID[Compendium.drsc-es-compendio-foundry.abilities.M2oXV5cRSdMlUZDm]{Incitar} @UUID[Compendium.drsc-es-compendio-foundry.abilities.Frxs35QkokRdure4]{Prestidigitación} @UUID[Compendium.drsc-es-compendio-foundry.abilities.90wkMwuVBaiyL9yt]{Oportunista} @UUID[Compendium.drsc-es-compendio-foundry.abilities.QAdh0yZBjJsHdJjD]{Habilidades de sigilo}</p><h3>Capacidades de Sigilo de Segundo Rango</h3><p>@UUID[Compendium.drsc-es-compendio-foundry.abilities.dQHSDDZxJNHrHH1l]{Contorsionista} @UUID[Compendium.drsc-es-compendio-foundry.abilities.8ydN3DBdXXP24hQL]{Encontrar una apertura} @UUID[Compendium.drsc-es-compendio-foundry.abilities.5abCQnz5ZWvvfMro]{Escapar} @UUID[Compendium.drsc-es-compendio-foundry.abilities.mvFsSsVjyF8iXvCe]{Sentir emboscadas} @UUID[Compendium.drsc-es-compendio-foundry.abilities.uG2ACHNAPoZirp0b]{Ataque sorpresa}</p><h3>Capacidades de Sigilo de Tercer Rango</h3><p>@UUID[Compendium.drsc-es-compendio-foundry.abilities.Uq6p6fOg9KyFcUws]{Evanescer} @UUID[Compendium.drsc-es-compendio-foundry.abilities.XR3B0gfJtrYUAU5M]{Desde las sombras} @UUID[Compendium.drsc-es-compendio-foundry.abilities.lUkqQu1vvJe3FxfQ]{Apostador} @UUID[Compendium.drsc-es-compendio-foundry.abilities.sM2zEDx4gRr9CuiR]{Defensa interior} @UUID[Compendium.drsc-es-compendio-foundry.abilities.lwJAowJa4eKlcDjb]{Desviar} @UUID[Compendium.drsc-es-compendio-foundry.abilities.ZuX6gykVtKxiBAxR]{Correr y luchar} @UUID[Compendium.drsc-es-compendio-foundry.abilities.t3zUlk8c5WEBXXO8]{Aprovechar el momento}</p><h3>Capacidades de Sigilo de Cuarto Rango</h3><p>@UUID[Compendium.drsc-es-compendio-foundry.abilities.cS1RW48sdVY6ZJZd]{Emboscador} @UUID[Compendium.drsc-es-compendio-foundry.abilities.JVvSTtYbksWJDADY]{Golpe debilitante} @UUID[Compendium.drsc-es-compendio-foundry.abilities.cqzyNCPYVEWtucLe]{Burlar} @UUID[Compendium.drsc-es-compendio-foundry.abilities.LojkwDtb1gHLSB6A]{Sentidos preternaturales} @UUID[Compendium.drsc-es-compendio-foundry.abilities.w2aO1ZIpmBDQJXq1]{Movimientos de voltereta}</p><h3>Capacidades de Sigilo de Quinto Rango</h3><p>@UUID[Compendium.drsc-es-compendio-foundry.abilities.YbYeZ0A0m96IWxwl]{Asesino Strike} @UUID[Compendium.drsc-es-compendio-foundry.abilities.S5JTyQCNcgrXgNqf]{Máscara} @UUID[Compendium.drsc-es-compendio-foundry.abilities.G5bTthwpEf5azVHA]{Regresar al remitente} @UUID[Compendium.drsc-es-compendio-foundry.abilities.bVt0TIfwtEUXvi6O]{Suerte asombrosa}</p><h3>Capacidades de Sigilo de Sexto Rango</h3><p>@UUID[Compendium.drsc-es-compendio-foundry.abilities.VVYx3J42Sj9qCQV9]{Explotar ventaja} @UUID[Compendium.drsc-es-compendio-foundry.abilities.jrTEtAhE6GfLW7R4]{Saltar lejos} @UUID[Compendium.drsc-es-compendio-foundry.abilities.cWHqKGpI5z0aiSYC]{Suerte de ladrón} @UUID[Compendium.drsc-es-compendio-foundry.abilities.aWws42dVSQjRz8Hr]{Giro del destino}</p><h1>Aspecto de Tecnología</h1><p>Los personajes con aspecto de tecnología suelen ser de ciencia ficción o, al menos, de escenarios modernos (aunque todo es posible). Destacan en el uso, manejo y construcción de máquinas. Un Explorador con aspecto de tecnología podría ser un piloto de naves estelares, y un Orador con aspecto de tecnología podría ser un tecno-sacerdote. Algunas de las capacidades menos orientadas a la informática podrían ser apropiadas para un personaje steampunk, mientras que un personaje moderno podría utilizar algunas de las capacidades que no tienen que ver con naves estelares o ultra-tecnología.</p><h3>Capacidades de Tecnología de Primer Rango</h3><p>@UUID[Compendium.drsc-es-compendio-foundry.abilities.Q3DGDFwNIOjz866X]{Datajack} @UUID[Compendium.drsc-es-compendio-foundry.abilities.z23towmNKeKJasHV]{Hacker} @UUID[Compendium.drsc-es-compendio-foundry.abilities.rhaZSmU6dJpzMO64]{Interfaz de máquinas} @UUID[Compendium.drsc-es-compendio-foundry.abilities.kkCW4KkWA751AeBl]{Confundir máquina} @UUID[Compendium.drsc-es-compendio-foundry.abilities.pYsmdnNte7o5Flca]{Tech Skills} @UUID[Compendium.drsc-es-compendio-foundry.abilities.AFfburUYwZlBFq7N]{Cacharrear}</p><h3>Capacidades de Tecnología de Segundo Rango</h3><p>@UUID[Compendium.drsc-es-compendio-foundry.abilities.7nUj7rxq4Qwg4FUM]{Interfaz a distancia} @UUID[Compendium.drsc-es-compendio-foundry.abilities.JK2hN1poqMLqfa1N]{Eficiencia de máquina} @UUID[Compendium.drsc-es-compendio-foundry.abilities.FDG7hgrRNt4aHpP1]{Sobrecargar máquina} @UUID[Compendium.drsc-es-compendio-foundry.abilities.v1lZkKjSCS1pjnET]{Serv-0} @UUID[Compendium.drsc-es-compendio-foundry.abilities.XzomXctsS8NL9M7Q]{Serv-0 defensor} @UUID[Compendium.drsc-es-compendio-foundry.abilities.x8cGd4MC9YEW9isa]{Serv-0 reparador} @UUID[Compendium.drsc-es-compendio-foundry.abilities.k4LeTZ1lqN9L3hPS]{Maestría en herramientas}</p><h3>Capacidades de Tecnología de Tercer Rango</h3><p>@UUID[Compendium.drsc-es-compendio-foundry.abilities.7VYzHQvF1cz4cfUp]{Telepatía mecánica} @UUID[Compendium.drsc-es-compendio-foundry.abilities.9r6iNU2GH4oEH6vz]{Serv-0 escáner} @UUID[Compendium.drsc-es-compendio-foundry.abilities.hIy0GMeL8WALvhEb]{Pies de nave} @UUID[Compendium.drsc-es-compendio-foundry.abilities.Nyt7Z1xWqmnuu265]{Naveparlar} @UUID[Compendium.drsc-es-compendio-foundry.abilities.YIzrA5i8eBSPMFzj]{Rociada}</p><h3>Capacidades de Tecnología de Cuarto Rango</h3><p>@UUID[Compendium.drsc-es-compendio-foundry.abilities.2l9FIUVKimPzIXzU]{Vínculo con máquina} @UUID[Compendium.drsc-es-compendio-foundry.abilities.NoKdHv0FSytZR4iF]{Cazador de robots} @UUID[Compendium.drsc-es-compendio-foundry.abilities.NcItnMHjeG9fgE1K]{Serv-0 apuntador} @UUID[Compendium.drsc-es-compendio-foundry.abilities.lPqCQOQJF0JfoFRn]{Serv-0 peleador} @UUID[Compendium.drsc-es-compendio-foundry.abilities.9YuQrJXAQO0qIFPj]{Serv-0 espía}</p><h3>Capacidades de Tecnología de Quinto Rango</h3><p>@UUID[Compendium.drsc-es-compendio-foundry.abilities.FxohCBSksJIu1BSA]{Controlar máquina} @UUID[Compendium.drsc-es-compendio-foundry.abilities.KQDFvUEnIWed1ebo]{Jury-Rig} @UUID[Compendium.drsc-es-compendio-foundry.abilities.XkFsMa9e9IY2FRcN]{Compañero máquina}</p><h3>Capacidades de Tecnología de Sexto Rango</h3><p>@UUID[Compendium.drsc-es-compendio-foundry.abilities.PLyxuOlieOGsJx4h]{Recabar información} @UUID[Compendium.drsc-es-compendio-foundry.abilities.7QTTrXnxDHskYYhj]{Maestro de máquina}</p><h1>Aspecto de Magia</h1><p>Sabes un poco de magia. Puede que no seas un mago, pero sabes lo básico: cómo funciona y cómo lograr algunas cosas maravillosas.</p><p>En tu entorno, \"magia\" puede significar poderes psíquicos o mutantes, tecnología alienígena o cualquier otra cosa que produzca efectos interesantes y útiles.</p><p>Un Explorador con aspecto de magia podría ser un mago-cazador, y un Orador con aspecto de magia podría ser un hechicero-bardo. Aunque un Adepto con aspecto de magia sigue siendo un Adepto, puedes encontrar que cambiar algunas de las habilidades básicas del tipo con las que se dan aquí acerca su PJ al concepto que quiere.</p><h3>Capacidades de Magia de Primer Rango</h3><p>@UUID[Compendium.drsc-es-compendio-foundry.abilities.I9m3nOdBZ2HoEmbj]{Bendición de los dioses} @UUID[Compendium.drsc-es-compendio-foundry.abilities.SQ4RTDwdA0yiZ81b]{Mente cerrada} @UUID[Compendium.drsc-es-compendio-foundry.abilities.bM2Y62eaUKYKdcwq]{Fuerza enredante} @UUID[Compendium.drsc-es-compendio-foundry.abilities.zArjjFcf9tHQvJTx]{Ardid mágico} @UUID[Compendium.drsc-es-compendio-foundry.abilities.XQxN55rl0f5HFxEM]{Entrenamiento mágico} @UUID[Compendium.drsc-es-compendio-foundry.abilities.TPEcyzCeC3z5FyyQ]{Enlace mental} @UUID[Compendium.drsc-es-compendio-foundry.abilities.ZsI6553CPbGi0wtx]{Premonición}</p><h3>Capacidades de Magia de Segundo Rango</h3><p>@UUID[Compendium.drsc-es-compendio-foundry.abilities.Mfebb42AE5xt7k85]{Explosión contundente} @UUID[Compendium.drsc-es-compendio-foundry.abilities.21Bi8yur01DCYz5f]{Traer} @UUID[Compendium.drsc-es-compendio-foundry.abilities.4fcns7ANpZF7pHaz]{Campo de fuerza} @UUID[Compendium.drsc-es-compendio-foundry.abilities.wNQ3q7VXtPHlPzqb]{Cerradura} @UUID[Compendium.drsc-es-compendio-foundry.abilities.rRDSzPJtUCwRVXFR]{Reparar carne}</p><h3>Capacidades de Magia de Tercer Rango</h3><p>@UUID[Compendium.drsc-es-compendio-foundry.abilities.MvyXo0ZUsxu8QQ22]{Visión a distancia} @UUID[Compendium.drsc-es-compendio-foundry.abilities.NgHLZq3tZ3CFJvYv]{Floración de fuego} @UUID[Compendium.drsc-es-compendio-foundry.abilities.CAh0KStmP03kgv62]{Arrojar} @UUID[Compendium.drsc-es-compendio-foundry.abilities.dDhnZrzAxDvK7QYa]{Fuerza a distancia} @UUID[Compendium.drsc-es-compendio-foundry.abilities.wEWyNKnVgVOjsyms]{Invocar araña gigante}</p><h3>Capacidades de Magia de Cuarto Rango</h3><p>@UUID[Compendium.drsc-es-compendio-foundry.abilities.XR8WeRW3OlbCIjlJ]{Protección elemental} @UUID[Compendium.drsc-es-compendio-foundry.abilities.LLvJZvzbGQOrlqoE]{Ignición} @UUID[Compendium.drsc-es-compendio-foundry.abilities.blm1Z8JxvWOiFf0b]{Abrir de par en par}</p><h3>Capacidades de Magia de Quinto Rango</h3><p>@UUID[Compendium.drsc-es-compendio-foundry.abilities.HuhNjMfMxPkTlERH]{Crear} @UUID[Compendium.drsc-es-compendio-foundry.abilities.OkKNmMvLFwHxUv2r]{Intervención divina} @UUID[Compendium.drsc-es-compendio-foundry.abilities.M1FHIlVPVv8O02LV]{Fauces de dragón} @UUID[Compendium.drsc-es-compendio-foundry.abilities.IKicLElFbkRx5IaM]{Viaje rápido} @UUID[Compendium.drsc-es-compendio-foundry.abilities.MGzAkRaGd4LgfQti]{Sentidos verdaderos}</p><h3>Capacidades de Magia de Sexto Rango</h3><p>@UUID[Compendium.drsc-es-compendio-foundry.abilities.RBOc2zxAI9xMoWqW]{Reubicar} @UUID[Compendium.drsc-es-compendio-foundry.abilities.LnZkUlKUuuD7iW3P]{Invocar demonio} @UUID[Compendium.drsc-es-compendio-foundry.abilities.PlKwEwo6ilGqwxwI]{Cruzar los mundos} @UUID[Compendium.drsc-es-compendio-foundry.abilities.Gsre3acJaxhGBa0S]{Palabra de muerte}</p><h1>Aspecto de Combate</h1><p>El aspecto de combate hace que un personaje sea más marcial. Un Orador con aspecto de combate en una ambientación de fantasía sería un bardo de batalla. Un Explorador con aspecto de combate en un juego histórico podría ser un pirata. Un Adepto con aspecto de combate en una ambientación de ciencia ficción podría ser un veterano de mil guerras psíquicas.</p><h3>Capacidades de Combate de Primer Rango</h3><p>@UUID[Compendium.drsc-es-compendio-foundry.abilities.UyQTRi5ZwWU5tMO0]{Sentido del peligro} @UUID[Compendium.drsc-es-compendio-foundry.abilities.o2ZDoteWQsFsqTJr]{Práctica en armaduras} @UUID[Compendium.drsc-es-compendio-foundry.abilities.NhijFGxYepJtaa0r]{Práctica en armas medias}</p><h3>Capacidades de Combate de Segundo Rango</h3><p>@UUID[Compendium.drsc-es-compendio-foundry.abilities.wyUQ3Atl3V1ItCFH]{Sed de sangre} @UUID[Compendium.drsc-es-compendio-foundry.abilities.2x7nMe9ZGp3VjI8B]{Destreza en el combate} @UUID[Compendium.drsc-es-compendio-foundry.abilities.uatcX3o1oB2Stc4u]{Entrenado sin armadura}</p><h3>Capacidades de Combate de Tercer Rango</h3><p>@UUID[Compendium.drsc-es-compendio-foundry.abilities.yl2zo179wXZW5Xxc]{Práctica en todas las armas} @UUID[Compendium.drsc-es-compendio-foundry.abilities.HHQzosgWahaIYPwk]{Habilidad ofensiva} @UUID[Compendium.drsc-es-compendio-foundry.abilities.CtRvLxfUlCynJv1B]{Habilidad defensiva} @UUID[Compendium.drsc-es-compendio-foundry.abilities.36nlDXhOP5e5dfns]{Ataque sucesivo}</p><h3>Capacidades de Combate de Cuarto Rango</h3><p>@UUID[Compendium.drsc-es-compendio-foundry.abilities.gNRMG3mJTzWaCGph]{Guerrero competente} @UUID[Compendium.drsc-es-compendio-foundry.abilities.Rr4oB1lUzuzFHNHQ]{Puntería letal} @UUID[Compendium.drsc-es-compendio-foundry.abilities.73miZT5kYFyxnPOT]{Furia} @UUID[Compendium.drsc-es-compendio-foundry.abilities.lwJAowJa4eKlcDjb]{Desviar} @UUID[Compendium.drsc-es-compendio-foundry.abilities.YIzrA5i8eBSPMFzj]{Rociada}</p><h3>Capacidades de Combate de Quinto Rango</h3><p>@UUID[Compendium.drsc-es-compendio-foundry.abilities.GlXd4oFI9Fqq3rAX]{Defensor experto} @UUID[Compendium.drsc-es-compendio-foundry.abilities.S9QxUr8u2gtwY7ya]{Objetivo difícil} @UUID[Compendium.drsc-es-compendio-foundry.abilities.AmZDmnmP7CxSSN4h]{Parada}</p><h3>Capacidades de Combate de Sexto Rango</h3><p>@UUID[Compendium.drsc-es-compendio-foundry.abilities.oroWEBbp3cvrYwH9]{Habilidad ofensiva mayor} @UUID[Compendium.drsc-es-compendio-foundry.abilities.4k5JFV78A5SiPjFo]{Maestría en armaduras} @UUID[Compendium.drsc-es-compendio-foundry.abilities.LTqgcoprvBF2ZkdH]{Maestría defensiva}</p><h1>Aspecto de Habilidades y Conocimientos</h1><p>Este aspecto es para los personajes que desempeñan funciones que requieren más conocimientos y una mayor aplicación del talento en el mundo real. Es menos llamativo y dramático que los poderes sobrenaturales o la capacidad de despedazar a múltiples enemigos, pero a veces la pericia o el saber hacer son la verdadera solución a un problema.</p><p>Un Guerrero con aspecto de habilidades y conocimientos podría ser un ingeniero militar. Un Explorador aspecto de habilidades y conocimientos podría ser un científico de campo. Un Orador con este aspecto podría ser un profesor.</p><h3>Capacidades de Habilidades y Conocimientos de Primer Rango</h3><p>@UUID[Compendium.drsc-es-compendio-foundry.abilities.V765JZKDKQ00Buyn]{Habilidades de interacción} @UUID[Compendium.drsc-es-compendio-foundry.abilities.romswZIOmAmtzfCL]{Habilidades de investigación} @UUID[Compendium.drsc-es-compendio-foundry.abilities.eEGFknWQZUBNXn99]{Habilidades de conocimiento} @UUID[Compendium.drsc-es-compendio-foundry.abilities.noCgrKbB370cfzQg]{Habilidades físicas} @UUID[Compendium.drsc-es-compendio-foundry.abilities.wEjdodvc6SLf8yso]{Habilidades de viaje}</p><h3>Capacidades de Habilidades y Conocimientos de Segundo Rango</h3><p>@UUID[Compendium.drsc-es-compendio-foundry.abilities.jx6DFmlbQrmltHgc]{Habilidad extra} @UUID[Compendium.drsc-es-compendio-foundry.abilities.k4LeTZ1lqN9L3hPS]{Maestría en herramientas} @UUID[Compendium.drsc-es-compendio-foundry.abilities.kv03xEihe4VZNkK5]{Comprensión}</p><h3>Capacidades de Habilidades y Conocimientos de Tercer Rango</h3><p>@UUID[Compendium.drsc-es-compendio-foundry.abilities.dVh39nh5ARUxreUc]{Habilidad flexible} @UUID[Compendium.drsc-es-compendio-foundry.abilities.uhC4ubTGfhkNvIMX]{Improvisar}</p><h3>Capacidades de Habilidades y Conocimientos de Cuarto Rango</h3><p>@UUID[Compendium.drsc-es-compendio-foundry.abilities.4USzF8qKs8oZJH13]{Habilidades múltiples} @UUID[Compendium.drsc-es-compendio-foundry.abilities.Mac5S0sQe9Muf4Mv]{Ingenio rápido} @UUID[Compendium.drsc-es-compendio-foundry.abilities.NaqoExT72j3xkWp3]{Especialización en tarea}</p><h3>Capacidades de Habilidades y Conocimientos de Quinto Rango</h3><p>@UUID[Compendium.drsc-es-compendio-foundry.abilities.NhijFGxYepJtaa0r]{Práctica en armas medias} @UUID[Compendium.drsc-es-compendio-foundry.abilities.lbXg8UlSCG23yxO4]{Leer las señales}</p><h3>Capacidades de Habilidades y Conocimientos de Sexto Rango</h3><p>@UUID[Compendium.drsc-es-compendio-foundry.abilities.HHQzosgWahaIYPwk]{Habilidad ofensiva} @UUID[Compendium.drsc-es-compendio-foundry.abilities.CtRvLxfUlCynJv1B]{Habilidad defensiva}</p>"
  },
  "_key": "!journal.pages!k9exUQdtIwtKwqCc.gUBd9dvLJ8qY0iZx"
}