{
  "img": "modules/drsc-es-compendio-foundry/img/tokens/elemental_earth.webp",
  "_stats": {
    "modifiedTime": 1676797809005,
    "systemId": "cyphersystem",
    "lastModifiedBy": "yThCrv1jSfPXOC2U",
    "createdTime": null,
    "systemVersion": "2.3.0",
    "coreVersion": "10.291"
  },
  "flags": {},
  "sort": 0,
  "type": "npc",
  "_key": "!actors!li1H57vGnKM9EY61",
  "prototypeToken": {
    "displayBars": 40,
    "displayName": 20,
    "actorLink": false,
    "lockRotation": false,
    "texture": {
      "scaleX": 1,
      "offsetX": 0,
      "scaleY": 1,
      "offsetY": 0,
      "src": "icons/svg/mystery-man.svg",
      "rotation": 0,
      "tint": null
    },
    "rotation": 0,
    "detectionModes": [],
    "flags": {},
    "randomImg": false,
    "bar1": {"attribute": "pools.health"},
    "bar2": {"attribute": "basic.level"},
    "disposition": 0,
    "light": {
      "attenuation": 0.5,
      "color": null,
      "bright": 0,
      "coloration": 1,
      "dim": 0,
      "animation": {
        "intensity": 5,
        "reverse": false,
        "type": null,
        "speed": 5
      },
      "saturation": 0,
      "alpha": 0.5,
      "contrast": 0,
      "angle": 360,
      "luminosity": 0.5,
      "shadows": 0,
      "darkness": {
        "min": 0,
        "max": 1
      }
    },
    "alpha": 1,
    "name": "Elemental de tierra",
    "width": 1,
    "sight": {
      "saturation": 0,
      "brightness": 1,
      "attenuation": 0.1,
      "color": null,
      "visionMode": "basic",
      "contrast": 0,
      "angle": 360,
      "range": 0,
      "enabled": false
    },
    "height": 1
  },
  "effects": [],
  "folder": null,
  "system": {
    "settings": {
      "skills": {},
      "abilities": {},
      "general": {
        "initiativeBonus": 0,
        "hideArchive": false
      },
      "equipment": {
        "ammo": {"active": false},
        "armor": {"active": false},
        "attacks": {"active": false},
        "materials": {
          "active": false,
          "label": ""
        },
        "cyphers": {
          "active": false,
          "label": ""
        },
        "oddities": {
          "active": false,
          "label": ""
        },
        "artifacts": {
          "active": false,
          "label": ""
        }
      }
    },
    "notes": "<p>Una excavación, la caída de un meteorito, un terremoto que aún tiembla... todos estos acontecimientos pueden convocar a un elemental de tierra para que tome forma y expanda aún más la destrucción.<\/p>\n<p><strong>Motivación:<\/strong> Desmenuzar y romper, reducir las cosas a la tierra<\/p>\n<p><strong>Entorno:<\/strong> Cualquier lugar sólido o de tierra<\/p>\n<p><strong>Salud:<\/strong> 30<\/p>\n<p><strong>Daño que inflige:<\/strong> 6 puntos<\/p>\n<p><strong>Armadura:<\/strong> 3<\/p>\n<p><strong>Movimiento:<\/strong> Inmediato; corto cuando se entierra<\/p>\n<p><strong>Combate:<\/strong> Los elementales de tierra golpean a los enemigos con sus pesados puños. También pueden crear terremotos (no más de una vez cada dos rondas) que afectan al suelo a corta distancia. Las criaturas que se encuentran en la zona caen al suelo y reciben 5 puntos de daño si fallan la tirada de Defensa por Vigor.<\/p>\n<p>Un elemental de tierra es vulnerable al agua. Cualquier daño que reciba mientras esté empapado o parado en agua ignora su Armadura.<\/p>\n<p><strong>Interacción:<\/strong> Aunque son taciturnos y tardan en responder si se encuentran como piedra inmóvil, los elementales de tierra son inteligentes. Los que son invocados con un hechizo tienen un 5% de posibilidades de romper el geas y volverse contra su invocador.<\/p>\n<p><strong>Uso:<\/strong> Se han descubierto extraños monolitos articulados en lo alto de las montañas alrededor de un santuario que contiene un antiguo tesoro. Un mercader quiere que alguien los investigue para saber si son una trampa. Mas los monolitos son elementales de tierra inactivos.<\/p>\n<p><strong>Intromisiones del DJ:<\/strong> Un PJ en el alcance del ataque de terremoto del elemental de tierra debe tener éxito en una tirada de Defensa por Velocidad o ser cubierto por una avalancha de escombros que se derrumban.<\/p>",
    "pools": {"health": {
      "max": 30,
      "value": 30
    }},
    "description": "",
    "combat": {
      "damage": 6,
      "armor": 3
    },
    "basic": {
      "level": 5,
      "biography": "<p>Una excavación, la caída de un meteorito, un terremoto que aún tiembla... todos estos acontecimientos pueden convocar a un elemental de tierra para que tome forma y expanda aún más la destrucción.<\/p>\n<p><strong>Motivación:<\/strong> Desmenuzar y romper, reducir las cosas a la tierra<\/p>\n<p><strong>Entorno:<\/strong> Cualquier lugar sólido o de tierra<\/p>\n<p><strong>Salud:<\/strong> 30<\/p>\n<p><strong>Daño que inflige:<\/strong> 6 puntos<\/p>\n<p><strong>Armadura:<\/strong> 3<\/p>\n<p><strong>Movimiento:<\/strong> Inmediato; corto cuando se entierra<\/p>\n<p><strong>Combate:<\/strong> Los elementales de tierra golpean a los enemigos con sus pesados puños. También pueden crear terremotos (no más de una vez cada dos rondas) que afectan al suelo a corta distancia. Las criaturas que se encuentran en la zona caen al suelo y reciben 5 puntos de daño si fallan la tirada de Defensa por Vigor.<\/p>\n<p>Un elemental de tierra es vulnerable al agua. Cualquier daño que reciba mientras esté empapado o parado en agua ignora su Armadura.<\/p>\n<p><strong>Interacción:<\/strong> Aunque son taciturnos y tardan en responder si se encuentran como piedra inmóvil, los elementales de tierra son inteligentes. Los que son invocados con un hechizo tienen un 5% de posibilidades de romper el geas y volverse contra su invocador.<\/p>\n<p><strong>Uso:<\/strong> Se han descubierto extraños monolitos articulados en lo alto de las montañas alrededor de un santuario que contiene un antiguo tesoro. Un mercader quiere que alguien los investigue para saber si son una trampa. Mas los monolitos son elementales de tierra inactivos.<\/p>\n<p><strong>Intromisiones del DJ:<\/strong> Un PJ en el alcance del ataque de terremoto del elemental de tierra debe tener éxito en una tirada de Defensa por Velocidad o ser cubierto por una avalancha de escombros que se derrumban.<\/p>"
    },
    "teen": {
      "settings": {},
      "pools": {},
      "basic": {}
    },
    "version": 2
  },
  "ownership": {
    "N1n5f3sdQOJFmoJe": 3,
    "default": 0
  },
  "name": "Elemental de tierra",
  "_id": "li1H57vGnKM9EY61",
  "items": []
}