{
  "img": "modules/drsc-es-compendio-foundry/img/tokens/fey_faerie.webp",
  "_stats": {
    "modifiedTime": 1685368971486,
    "systemId": "cyphersystem",
    "lastModifiedBy": "yThCrv1jSfPXOC2U",
    "createdTime": 1676279040601,
    "systemVersion": "2.6.0",
    "coreVersion": "10.291"
  },
  "flags": {"core": {"sourceId": "Actor.YbqqaHSom0SOcCia"}},
  "sort": 0,
  "type": "npc",
  "_key": "!actors!ZoyQXTMuKbJr8vvg",
  "prototypeToken": {
    "displayBars": 40,
    "displayName": 20,
    "actorLink": false,
    "texture": {
      "scaleX": 1,
      "offsetX": 0,
      "scaleY": 1,
      "offsetY": 0,
      "src": "icons/svg/mystery-man.svg",
      "rotation": 0,
      "tint": null
    },
    "lockRotation": true,
    "rotation": 0,
    "detectionModes": [],
    "flags": {"barbrawl": {"resourceBars": {
      "bar1": {
        "hideCombat": false,
        "bgImage": "",
        "hideNoCombat": false,
        "hideFull": false,
        "otherVisibility": 0,
        "indentRight": null,
        "subdivisionsOwner": false,
        "id": "bar1",
        "attribute": "pools.health",
        "ownerVisibility": 50,
        "hideEmpty": false,
        "indentLeft": null,
        "order": 0,
        "shareHeight": false,
        "invert": false,
        "label": "",
        "fgImage": "",
        "maxcolor": "#80FF00",
        "gmVisibility": -1,
        "style": "user",
        "mincolor": "#FF0000",
        "position": "bottom-inner",
        "opacity": null,
        "invertDirection": false,
        "subdivisions": null
      },
      "bar2": {
        "hideCombat": false,
        "bgImage": "",
        "hideNoCombat": false,
        "hideFull": false,
        "otherVisibility": 0,
        "indentRight": null,
        "subdivisionsOwner": false,
        "id": "bar2",
        "attribute": "basic.level",
        "ownerVisibility": 50,
        "hideEmpty": false,
        "indentLeft": null,
        "order": 1,
        "shareHeight": false,
        "invert": false,
        "max": null,
        "label": "",
        "fgImage": "",
        "maxcolor": "#80B3FF",
        "gmVisibility": -1,
        "style": "user",
        "mincolor": "#000080",
        "position": "top-inner",
        "opacity": null,
        "invertDirection": false,
        "subdivisions": null
      }
    }}},
    "randomImg": false,
    "bar1": {"attribute": "pools.health"},
    "bar2": {"attribute": "basic.level"},
    "disposition": 0,
    "light": {
      "attenuation": 0.5,
      "color": null,
      "bright": 0,
      "coloration": 1,
      "dim": 0,
      "animation": {
        "intensity": 5,
        "type": null,
        "reverse": false,
        "speed": 5
      },
      "saturation": 0,
      "alpha": 0.5,
      "contrast": 0,
      "angle": 360,
      "luminosity": 0.5,
      "shadows": 0,
      "darkness": {
        "min": 0,
        "max": 1
      }
    },
    "alpha": 1,
    "name": "Hada (Cuentos de hádas)",
    "width": 1,
    "sight": {
      "saturation": 0,
      "attenuation": 0.1,
      "brightness": 0,
      "color": null,
      "visionMode": "basic",
      "contrast": 0,
      "range": null,
      "angle": 360,
      "enabled": false
    },
    "height": 1
  },
  "effects": [],
  "system": {
    "settings": {
      "general": {
        "initiativeBonus": 0,
        "hideArchive": false
      },
      "equipment": {
        "ammo": {"active": false},
        "armor": {"active": false},
        "attacks": {"active": false},
        "materials": {
          "active": false,
          "label": ""
        },
        "cyphers": {
          "active": false,
          "label": ""
        },
        "oddities": {
          "active": false,
          "label": ""
        },
        "artifacts": {
          "active": false,
          "label": ""
        }
      }
    },
    "notes": "<p>En general, las hadas son humanoides, de pequeña estatura y mágicas. Se asocian con la música, la alegría, los trucos y las burlas. Ver una es un presagio, con suerte, el presagio de una canción tonta o la primera aparición de un nuevo y molesto compañero de camino (la propia hada avistada) revoloteando por ahí, haciendo las preguntas de un curioso niño de cuatro años embriagado de agua azucarada y helado. Algunas hadas son tricksters, les encanta gastar bromas y robar ropa, equipo u objetos preciados. Otras son maliciosas, atraen a los viajeros a sus destinos, hacen tratos mortales y obligan a otros a permanecer cautivos.<\/p>\n<p>No todas las hadas tienen alas, pero las que las tienen encuentran muchas formas de utilizarlas en su beneficio.<\/p>\n<p><strong>Motivación:<\/strong> Impredecible<\/p>\n<p><strong>Entorno:<\/strong> Se encuentran solas o en bandadas de tres a doce, normalmente en bosques<\/p>\n<p><strong>Salud:<\/strong> 12<\/p>\n<p><strong>Daño que inflige:<\/strong> 4 puntos<\/p>\n<p><strong>Movimiento:<\/strong> Inmediato; largo al volar<\/p>\n<p><strong>Ajustes:<\/strong> Nivel 5 para tareas relacionadas con artes escénicas y engaño; nivel 5 para Defensa por velocidad debido a su tamaño y rapidez<\/p>\n<p><strong>Combate:<\/strong> Un hada ataca lanzando polvo mágico centelleante a un objetivo a corta distancia. Además, si un hada es tocada o golpeada por un arma cuerpo a cuerpo, más polvo mágico sale despedido del hada y nubla al atacante, que debe tener éxito en una tarea de Defensa por Velocidad o sufrir la misma cantidad de daño que acaba de infligir al hada. A veces las hadas empuñan armas pequeñas, como arcos, lanzas o espadas; trátalas como armas ligeras.<\/p>\n<p>Un hada puede ver en la oscuridad, pero también puede emitir luz brillante (a menudo de colores) y aparecer como un humanoide resplandeciente o una esfera iluminada.<\/p>\n<p>Las hadas recuperan 1 punto de Vida por ronda mientras su Salud esté por encima de 0, a menos que hayan sido dañadas con un arma argentada o de hierro frío.<\/p>\n<p>Además de infligir daño con su polvo de hadas y las armas que elijan, las hadas disponen de una serie de maldiciones y capacidades. Entre ellas se incluyen las siguientes:<\/p>\n<p><strong>Amigo de los animales:<\/strong> La mayoría de las hadas pueden comunicarse con los animales, y unas pocas pueden incluso invocar animales a larga distancia para que les ayuden y protejan. Algunas hadas también pueden conceder a otros la capacidad de comunicarse con los animales, pero sólo durante un día.<\/p>\n<p><strong>Hechizar:<\/strong> Algunas hadas pueden intentar usar una canción o un despliegue de luz para hechizar a otros a corta distancia. El objetivo debe tener éxito en una tarea de Defensa por Intelecto o caer en un estado de sugestión durante una hora. Durante este periodo, el objetivo puede ser dirigido por el hada hasta que sea atacado, dañado o sacudido de su encanto.<\/p>\n<p><strong>Clarividencia:<\/strong> El hada concede a alguien la capacidad de ver el futuro, el pasado, las hadas o uno de los mundos ocultos de las hadas. Este don dura un día, o hasta que el personaje haga una tirada de recuperación de diez horas.<\/p>\n<p><strong>Curar:<\/strong> el hada se cura a sí misma, a una planta, a una criatura o a otro personaje 1d6 + 2 puntos de daño.<\/p>\n<p><strong>Ilusión:<\/strong> Las hadas poderosas pueden lanzar elaboradas y convincentes ilusiones que hacen que ellas y sus mundos parezcan más atractivos y bellos. Las ilusiones pueden cubrir hasta una milla de área. Ver a través de la ilusión es una tarea igual al nivel del hada y dura diez minutos. Después de eso, el espectador vuelve a ver la ilusión y olvida rápidamente que vio algo más.<\/p>\n<p><strong>Invisibilidad:<\/strong> Hace al hada invisible a la mayoría de los ojos. Ver, oír o sentir a un hada cuando es invisible es una tarea igual al nivel del hada. Un intento fallido de ver un hada hace que el espectador vea algo que daña su mente, infligiendo 1 punto de daño de Intelecto.<\/p>\n<p><strong>Vórtice:<\/strong> Una táctica defensiva en la que una o más hadas amenazadas utilizan sus alas para crear una fuerte ráfaga de viento, tornado o vórtice. El viento hace retroceder a sus enemigos una gran distancia y les inflige 2 puntos de daño.<\/p>\n<p>Las hadas tienen una gran variedad de debilidades, como la plata, el hierro, la tecnología, el azúcar y la sal (deben contar cada grano) y la nata (las intoxica). Pero no todas las hadas tienen las mismas debilidades, y algunas pueden no tener ninguna.<\/p>\n<p><strong>Interacción:<\/strong> Las hadas son criaturas volubles, pero excepto las maliciosas, se puede negociar con ellas, especialmente si se les ofrecen dulces, vino, crema u otros regalos. Dicho esto, la capacidad de atención de las hadas es limitada, por lo que incluso una que tenga buenas intenciones podría acabar dejando a los PJs en la estacada justo en el momento equivocado.<\/p>\n<p><strong>Uso:<\/strong> Los personajes se encuentran con un hada herida, que promete concederles su deseo más profundo si aceptan ayudarla. Deben decidir si creen que el hada habla en serio o si se trata de una trampa.<\/p>\n<p><strong>Botín:<\/strong> Las pequeñas bolsas que llevan las hadas están llenas de baratijas del bosque, pero algunas de esas bolsas son diez veces más grandes por dentro y podrían contener objetos caros o Cyphers.<\/p>\n<p><strong>Intromisiones del DJ:<\/strong> Un personaje hace accidentalmente algo que ofende a un hada servicial, provocando que se vuelva contra él.<\/p>",
    "pools": {"health": {
      "max": 12,
      "value": 12
    }},
    "description": "",
    "combat": {
      "damage": 4,
      "armor": 0
    },
    "basic": {
      "level": 3,
      "biography": "<p>En general, las hadas son humanoides, de pequeña estatura y mágicas. Se asocian con la música, la alegría, los trucos y las burlas. Ver una es un presagio, con suerte, el presagio de una canción tonta o la primera aparición de un nuevo y molesto compañero de camino (la propia hada avistada) revoloteando por ahí, haciendo las preguntas de un curioso niño de cuatro años embriagado de agua azucarada y helado. Algunas hadas son tricksters, les encanta gastar bromas y robar ropa, equipo u objetos preciados. Otras son maliciosas, atraen a los viajeros a sus destinos, hacen tratos mortales y obligan a otros a permanecer cautivos.<\/p>\n<p>No todas las hadas tienen alas, pero las que las tienen encuentran muchas formas de utilizarlas en su beneficio.<\/p>\n<p><strong>Motivación:<\/strong> Impredecible<\/p>\n<p><strong>Entorno:<\/strong> Se encuentran solas o en bandadas de tres a doce, normalmente en bosques<\/p>\n<p><strong>Salud:<\/strong> 12<\/p>\n<p><strong>Daño que inflige:<\/strong> 4 puntos<\/p>\n<p><strong>Movimiento:<\/strong> Inmediato; largo al volar<\/p>\n<p><strong>Ajustes:<\/strong> Nivel 5 para tareas relacionadas con artes escénicas y engaño; nivel 5 para Defensa por velocidad debido a su tamaño y rapidez<\/p>\n<p><strong>Combate:<\/strong> Un hada ataca lanzando polvo mágico centelleante a un objetivo a corta distancia. Además, si un hada es tocada o golpeada por un arma cuerpo a cuerpo, más polvo mágico sale despedido del hada y nubla al atacante, que debe tener éxito en una tarea de Defensa por Velocidad o sufrir la misma cantidad de daño que acaba de infligir al hada. A veces las hadas empuñan armas pequeñas, como arcos, lanzas o espadas; trátalas como armas ligeras.<\/p>\n<p>Un hada puede ver en la oscuridad, pero también puede emitir luz brillante (a menudo de colores) y aparecer como un humanoide resplandeciente o una esfera iluminada.<\/p>\n<p>Las hadas recuperan 1 punto de Vida por ronda mientras su Salud esté por encima de 0, a menos que hayan sido dañadas con un arma argentada o de hierro frío.<\/p>\n<p>Además de infligir daño con su polvo de hadas y las armas que elijan, las hadas disponen de una serie de maldiciones y capacidades. Entre ellas se incluyen las siguientes:<\/p>\n<p><strong>Amigo de los animales:<\/strong> La mayoría de las hadas pueden comunicarse con los animales, y unas pocas pueden incluso invocar animales a larga distancia para que les ayuden y protejan. Algunas hadas también pueden conceder a otros la capacidad de comunicarse con los animales, pero sólo durante un día.<\/p>\n<p><strong>Hechizar:<\/strong> Algunas hadas pueden intentar usar una canción o un despliegue de luz para hechizar a otros a corta distancia. El objetivo debe tener éxito en una tarea de Defensa por Intelecto o caer en un estado de sugestión durante una hora. Durante este periodo, el objetivo puede ser dirigido por el hada hasta que sea atacado, dañado o sacudido de su encanto.<\/p>\n<p><strong>Clarividencia:<\/strong> El hada concede a alguien la capacidad de ver el futuro, el pasado, las hadas o uno de los mundos ocultos de las hadas. Este don dura un día, o hasta que el personaje haga una tirada de recuperación de diez horas.<\/p>\n<p><strong>Curar:<\/strong> el hada se cura a sí misma, a una planta, a una criatura o a otro personaje 1d6 + 2 puntos de daño.<\/p>\n<p><strong>Ilusión:<\/strong> Las hadas poderosas pueden lanzar elaboradas y convincentes ilusiones que hacen que ellas y sus mundos parezcan más atractivos y bellos. Las ilusiones pueden cubrir hasta una milla de área. Ver a través de la ilusión es una tarea igual al nivel del hada y dura diez minutos. Después de eso, el espectador vuelve a ver la ilusión y olvida rápidamente que vio algo más.<\/p>\n<p><strong>Invisibilidad:<\/strong> Hace al hada invisible a la mayoría de los ojos. Ver, oír o sentir a un hada cuando es invisible es una tarea igual al nivel del hada. Un intento fallido de ver un hada hace que el espectador vea algo que daña su mente, infligiendo 1 punto de daño de Intelecto.<\/p>\n<p><strong>Vórtice:<\/strong> Una táctica defensiva en la que una o más hadas amenazadas utilizan sus alas para crear una fuerte ráfaga de viento, tornado o vórtice. El viento hace retroceder a sus enemigos una gran distancia y les inflige 2 puntos de daño.<\/p>\n<p>Las hadas tienen una gran variedad de debilidades, como la plata, el hierro, la tecnología, el azúcar y la sal (deben contar cada grano) y la nata (las intoxica). Pero no todas las hadas tienen las mismas debilidades, y algunas pueden no tener ninguna.<\/p>\n<p><strong>Interacción:<\/strong> Las hadas son criaturas volubles, pero excepto las maliciosas, se puede negociar con ellas, especialmente si se les ofrecen dulces, vino, crema u otros regalos. Dicho esto, la capacidad de atención de las hadas es limitada, por lo que incluso una que tenga buenas intenciones podría acabar dejando a los PJs en la estacada justo en el momento equivocado.<\/p>\n<p><strong>Uso:<\/strong> Los personajes se encuentran con un hada herida, que promete concederles su deseo más profundo si aceptan ayudarla. Deben decidir si creen que el hada habla en serio o si se trata de una trampa.<\/p>\n<p><strong>Botín:<\/strong> Las pequeñas bolsas que llevan las hadas están llenas de baratijas del bosque, pero algunas de esas bolsas son diez veces más grandes por dentro y podrían contener objetos caros o Cyphers.<\/p>\n<p><strong>Intromisiones del DJ:<\/strong> Un personaje hace accidentalmente algo que ofende a un hada servicial, provocando que se vuelva contra él.<\/p>"
    },
    "version": 2
  },
  "folder": null,
  "ownership": {
    "default": 0,
    "yThCrv1jSfPXOC2U": 3
  },
  "name": "Hada (Cuentos de hádas)",
  "_id": "ZoyQXTMuKbJr8vvg",
  "items": []
}