{
  "img": "modules/drsc-es-compendio-foundry/img/tokens/humanoid_mundane.webp",
  "_stats": {
    "modifiedTime": 1676797809222,
    "systemId": "cyphersystem",
    "lastModifiedBy": "yThCrv1jSfPXOC2U",
    "createdTime": 1676287359368,
    "systemVersion": "2.3.0",
    "coreVersion": "10.291"
  },
  "flags": {"core": {"sourceId": "Actor.NftZOsRB61TjvVeM"}},
  "sort": 0,
  "type": "npc",
  "_key": "!actors!ymZTl25jXnMdWEh8",
  "prototypeToken": {
    "displayBars": 40,
    "displayName": 20,
    "actorLink": false,
    "texture": {
      "scaleX": 1,
      "offsetX": 0,
      "scaleY": 1,
      "offsetY": 0,
      "src": "icons/svg/mystery-man.svg",
      "rotation": 0,
      "tint": null
    },
    "lockRotation": false,
    "rotation": 0,
    "detectionModes": [],
    "flags": {},
    "randomImg": false,
    "bar1": {"attribute": "pools.health"},
    "bar2": {"attribute": "basic.level"},
    "disposition": 0,
    "light": {
      "attenuation": 0.5,
      "color": null,
      "bright": 0,
      "coloration": 1,
      "dim": 0,
      "animation": {
        "intensity": 5,
        "type": null,
        "reverse": false,
        "speed": 5
      },
      "saturation": 0,
      "alpha": 0.5,
      "contrast": 0,
      "angle": 360,
      "luminosity": 0.5,
      "shadows": 0,
      "darkness": {
        "min": 0,
        "max": 1
      }
    },
    "alpha": 1,
    "name": "Caballero noble",
    "width": 1,
    "sight": {
      "saturation": 0,
      "attenuation": 0.1,
      "brightness": 0,
      "color": null,
      "visionMode": "basic",
      "contrast": 0,
      "range": null,
      "angle": 360,
      "enabled": false
    },
    "height": 1
  },
  "effects": [],
  "system": {
    "settings": {
      "general": {
        "initiativeBonus": 0,
        "hideArchive": false
      },
      "equipment": {
        "ammo": {"active": false},
        "armor": {"active": false},
        "attacks": {"active": false},
        "materials": {
          "active": false,
          "label": ""
        },
        "cyphers": {
          "active": false,
          "label": ""
        },
        "oddities": {
          "active": false,
          "label": ""
        },
        "artifacts": {
          "active": false,
          "label": ""
        }
      }
    },
    "notes": "<p>Ya sean nobles o innobles, algunos caballeros alcanzan un dominio asombroso sobre las armas, el combate y las gracias cortesanas, eclipsando a guerreros y campeones menores. Las misiones de algunos caballeros nobles pueden llevarles lejos a través de la tierra, a nuevos y extraños territorios donde encuentran y derrotan a varias criaturas mágicas.<\/p>\n<p><strong>Motivación:<\/strong> Llevar a cabo hazañas nobles (o innobles).<\/p>\n<p><strong>Entorno:<\/strong> Casi cualquier lugar, a menudo solo, a veces con seguidores<\/p>\n<p><strong>Salud:<\/strong> 50<\/p>\n<p><strong>Daño que inflige:<\/strong> 10 puntos<\/p>\n<p><strong>Armadura:<\/strong> 3<\/p>\n<p><strong>Movimiento:<\/strong> Corto<\/p>\n<p><strong>Ajustes: <\/strong>Nivel 8 para todas las tareas relacionadas con heráldica y caballería; nivel 8 para Defensa por Velocidad mientras sostiene el escudo.<\/p>\n<p><strong>Combate:<\/strong> Los caballeros nobles van armados con armas macizas que pueden blandir con una sola mano, lo que significa que también pueden sostener un escudo. Son hábiles con las armas melé (como el hacha de guerra, el sable o la maza) e infligen un daño letal al impactar.<\/p>\n<p>Los caballeros nobles también pueden contar con la ayuda de uno o dos artefactos mágicos y, posiblemente, de un corcel noble (<strong>Corcel noble:<\/strong> nivel 5; se mueve una distancia larga cada ronda). El artefacto puede ser la propia arma que un caballero empuñe en combate y podría otorgarle una o más de las siguientes habilidades adicionales:<\/p>\n<p><strong>Fuerza Legendaria:<\/strong> El caballero noble puede invocar el artefacto para que le conceda una gran fuerza o fortaleza para realizar una tarea física concreta (como derribar una puerta, levantar una roca o derribar los pilares que sostienen una estructura), que intentará como si fuera de nivel 10.<\/p>\n<p><strong>Regeneración:<\/strong> El caballero noble regenera 2 puntos de salud por ronda mientras el arma esté desenvainada.<\/p>\n<p><strong>Resistencia:<\/strong> El caballero noble es inmune a los efectos que puedan influir en su mente, hechizarlo o dormirlo.<\/p>\n<p><strong>Interacción:<\/strong> El lenguaje florido y los modales impecables muestran el origen noble de un caballero. Aquellos que negocian con él de buena fe suelen llevarse algo de valor. Sin embargo, a veces un caballero noble es corrupto y traiciona la confianza.<\/p>\n<p><strong>Uso:<\/strong> Un caballero noble ha decidido que debe proteger un puente de cualquiera que quiera cruzarlo.<\/p>\n<p><strong>Botín:<\/strong> Los caballeros nobles llevan armas, armaduras pesadas y quizás un Cypher o incluso un artefacto.<\/p>\n<p><strong>Intromisiones del DJ:<\/strong> El personaje dañado por el ataque de un caballero noble debe tener éxito en una tirada de Defensa por Vigor o ser derribado de una montura, un puente o un acantilado, o, si nada es adecuado, es derribado al suelo y queda fuera del alcance inmediato del caballero.<\/p>",
    "pools": {"health": {
      "max": 50,
      "value": 50
    }},
    "description": "",
    "combat": {
      "damage": 10,
      "armor": 3
    },
    "basic": {
      "level": 7,
      "biography": "<p>Ya sean nobles o innobles, algunos caballeros alcanzan un dominio asombroso sobre las armas, el combate y las gracias cortesanas, eclipsando a guerreros y campeones menores. Las misiones de algunos caballeros nobles pueden llevarles lejos a través de la tierra, a nuevos y extraños territorios donde encuentran y derrotan a varias criaturas mágicas.<\/p>\n<p><strong>Motivación:<\/strong> Llevar a cabo hazañas nobles (o innobles).<\/p>\n<p><strong>Entorno:<\/strong> Casi cualquier lugar, a menudo solo, a veces con seguidores<\/p>\n<p><strong>Salud:<\/strong> 50<\/p>\n<p><strong>Daño que inflige:<\/strong> 10 puntos<\/p>\n<p><strong>Armadura:<\/strong> 3<\/p>\n<p><strong>Movimiento:<\/strong> Corto<\/p>\n<p><strong>Ajustes: <\/strong>Nivel 8 para todas las tareas relacionadas con heráldica y caballería; nivel 8 para Defensa por Velocidad mientras sostiene el escudo.<\/p>\n<p><strong>Combate:<\/strong> Los caballeros nobles van armados con armas macizas que pueden blandir con una sola mano, lo que significa que también pueden sostener un escudo. Son hábiles con las armas melé (como el hacha de guerra, el sable o la maza) e infligen un daño letal al impactar.<\/p>\n<p>Los caballeros nobles también pueden contar con la ayuda de uno o dos artefactos mágicos y, posiblemente, de un corcel noble (<strong>Corcel noble:<\/strong> nivel 5; se mueve una distancia larga cada ronda). El artefacto puede ser la propia arma que un caballero empuñe en combate y podría otorgarle una o más de las siguientes habilidades adicionales:<\/p>\n<p><strong>Fuerza Legendaria:<\/strong> El caballero noble puede invocar el artefacto para que le conceda una gran fuerza o fortaleza para realizar una tarea física concreta (como derribar una puerta, levantar una roca o derribar los pilares que sostienen una estructura), que intentará como si fuera de nivel 10.<\/p>\n<p><strong>Regeneración:<\/strong> El caballero noble regenera 2 puntos de salud por ronda mientras el arma esté desenvainada.<\/p>\n<p><strong>Resistencia:<\/strong> El caballero noble es inmune a los efectos que puedan influir en su mente, hechizarlo o dormirlo.<\/p>\n<p><strong>Interacción:<\/strong> El lenguaje florido y los modales impecables muestran el origen noble de un caballero. Aquellos que negocian con él de buena fe suelen llevarse algo de valor. Sin embargo, a veces un caballero noble es corrupto y traiciona la confianza.<\/p>\n<p><strong>Uso:<\/strong> Un caballero noble ha decidido que debe proteger un puente de cualquiera que quiera cruzarlo.<\/p>\n<p><strong>Botín:<\/strong> Los caballeros nobles llevan armas, armaduras pesadas y quizás un Cypher o incluso un artefacto.<\/p>\n<p><strong>Intromisiones del DJ:<\/strong> El personaje dañado por el ataque de un caballero noble debe tener éxito en una tirada de Defensa por Vigor o ser derribado de una montura, un puente o un acantilado, o, si nada es adecuado, es derribado al suelo y queda fuera del alcance inmediato del caballero.<\/p>"
    },
    "version": 2
  },
  "folder": null,
  "ownership": {
    "default": 0,
    "yThCrv1jSfPXOC2U": 3
  },
  "name": "Caballero noble",
  "_id": "ymZTl25jXnMdWEh8",
  "items": []
}