{
  "img": "modules/drsc-es-compendio-foundry/img/tokens/vermin_insect.webp",
  "_stats": {
    "modifiedTime": 1681829728840,
    "systemId": "cyphersystem",
    "lastModifiedBy": "yThCrv1jSfPXOC2U",
    "createdTime": 1676460010047,
    "systemVersion": "2.5.0",
    "coreVersion": "10.291"
  },
  "flags": {"core": {"sourceId": "Actor.4eygwJnYK2Y0JA10"}},
  "sort": 0,
  "type": "npc",
  "_key": "!actors!r6w6T9wXYqlk7zZE",
  "prototypeToken": {
    "displayBars": 50,
    "displayName": 20,
    "actorLink": false,
    "texture": {
      "scaleX": 1,
      "offsetX": 0,
      "scaleY": 1,
      "offsetY": 0,
      "src": "icons/svg/mystery-man.svg",
      "rotation": 0,
      "tint": null
    },
    "lockRotation": false,
    "rotation": 0,
    "detectionModes": [],
    "flags": {"barbrawl": {"resourceBars": {
      "bar1": {
        "hideCombat": false,
        "bgImage": "",
        "hideNoCombat": false,
        "hideFull": false,
        "otherVisibility": 0,
        "indentRight": null,
        "subdivisionsOwner": false,
        "id": "bar1",
        "attribute": "pools.health",
        "ownerVisibility": 50,
        "hideEmpty": false,
        "indentLeft": null,
        "order": 0,
        "shareHeight": false,
        "invert": false,
        "label": "",
        "fgImage": "",
        "maxcolor": "#80FF00",
        "gmVisibility": -1,
        "style": "user",
        "mincolor": "#FF0000",
        "position": "bottom-inner",
        "opacity": null,
        "invertDirection": false,
        "subdivisions": null
      },
      "bar2": {
        "hideCombat": false,
        "bgImage": "",
        "hideNoCombat": false,
        "hideFull": false,
        "otherVisibility": 0,
        "indentRight": null,
        "subdivisionsOwner": false,
        "id": "bar2",
        "attribute": "basic.level",
        "ownerVisibility": 50,
        "hideEmpty": false,
        "indentLeft": null,
        "order": 1,
        "shareHeight": false,
        "invert": false,
        "max": null,
        "label": "",
        "fgImage": "",
        "maxcolor": "#80B3FF",
        "gmVisibility": -1,
        "style": "user",
        "mincolor": "#000080",
        "position": "top-inner",
        "opacity": null,
        "invertDirection": false,
        "subdivisions": null
      }
    }}},
    "randomImg": false,
    "bar1": {"attribute": "pools.health"},
    "bar2": {"attribute": "basic.level"},
    "disposition": 0,
    "light": {
      "attenuation": 0.5,
      "color": null,
      "bright": 0,
      "coloration": 1,
      "dim": 0,
      "animation": {
        "intensity": 5,
        "type": null,
        "reverse": false,
        "speed": 5
      },
      "saturation": 0,
      "alpha": 0.5,
      "contrast": 0,
      "angle": 360,
      "luminosity": 0.5,
      "shadows": 0,
      "darkness": {
        "min": 0,
        "max": 1
      }
    },
    "alpha": 1,
    "name": "Parásito de silicio",
    "width": 1,
    "sight": {
      "saturation": 0,
      "attenuation": 0.1,
      "brightness": 0,
      "color": null,
      "visionMode": "basic",
      "contrast": 0,
      "range": null,
      "angle": 360,
      "enabled": false
    },
    "height": 1
  },
  "effects": [],
  "system": {
    "settings": {
      "general": {
        "initiativeBonus": 0,
        "hideArchive": false
      },
      "equipment": {
        "ammo": {"active": false},
        "armor": {"active": false},
        "attacks": {"active": false},
        "materials": {
          "active": false,
          "label": ""
        },
        "cyphers": {
          "active": false,
          "label": ""
        },
        "oddities": {
          "active": false,
          "label": ""
        },
        "artifacts": {
          "active": false,
          "label": ""
        }
      }
    },
    "notes": "<p>Estas diminutas criaturas plateadas con aspecto de insecto tienen un tamaño que oscila entre el submilímetro y los 30 cm [1 pie] de diámetro, y emiten breves pulsos de luz láser de color violeta para detectar y tomar muestras de su entorno. Compuestos de alambres y obleas de silicio orgánico, y autoensamblados o evolucionados en algún laboratorio o nave espacial sin nombre, los parásitos de silicio son alimañas que las estaciones y naves espaciales en funcionamiento han aprendido a odiar. A pesar de tomar medidas para evitar su transferencia, una nave sólo puede enterarse de que tiene parásitos de silicio cuando un enjambre brota de una grieta en el cableado o de una costura en el revestimiento de la cubierta después de haber sido agitado por una maniobra de alta-G o alguna otra perturbación. Si esa perturbación es un combate o alguna otra emergencia extrema, los parásitos de silicio arrojados a la situación lo empeoran todo.<\/p>\n<p><strong>Motivación:<\/strong> Defensa, recolectar materiales electrónicos necesarios para autorreplicarse.<\/p>\n<p><strong>Entorno:<\/strong> Normalmente en naves espaciales y estaciones espaciales en grupos de hasta veinte.<\/p>\n<p><strong>Salud:<\/strong> 6<\/p>\n<p><strong>Daño que inflige: <\/strong>3 puntos<\/p>\n<p><strong>Armadura:<\/strong> 1<\/p>\n<p><strong>Movimiento:<\/strong> Corto; sube una distancia corta cada ronda<\/p>\n<p><strong>Ajustes:<\/strong> Nivel 4 para Defensa por Velocidad debido al tamaño.<\/p>\n<p><strong>Combate:<\/strong> Sólo los parásitos de silicio \"grandes\" son un peligro para la mayoría de las criaturas. Cuando cuatro o más parásitos coordinan sus ataques, trata el ataque como el realizado por una sola criatura de nivel 4 que inflige 5 puntos de daño, y con una tirada fallida de Defensa por Vigor de dificultad 4, un ataque que retiene al objetivo hasta que pueda escapar con éxito. Un objetivo retenido recibe automáticamente 5 puntos de daño cada ronda, o incluso más si se acumulan otros parásitos de silicio en la zona. Los parásitos de silicio pueden operar en el vacío completo sin sufrir daños.<\/p>\n<p><strong>Interacción:<\/strong> En general, los parásitos de silicio se comportan como insectos sociales, aunque algunos afirman que un gran número de ellos han actuado con mayor inteligencia y previsión de lo que los simples insectos irreflexivos pueden conseguir.<\/p>\n<p><strong>Uso: <\/strong>Un enjambre de parásitos de silicio inunda la bodega y se hace con un artefacto importante, arrastrándolo por las grietas y paredes de la nave espacial o estación.<\/p>\n<p><strong>Botín: <\/strong>Los nidos de enjambre a menudo contienen algunos Cyphers manifiestos valiosos o piezas de equipo que funcionan.<\/p>\n<p><strong>Intromisiones del DJ:<\/strong> El parásito de silicio dispara su láser sensorial directamente a los ojos del personaje, cegándolo hasta que tenga éxito en una tirada basada en el Vigor de dificultad 4 como su acción.<\/p>",
    "pools": {"health": {
      "max": 6,
      "value": 6
    }},
    "description": "",
    "combat": {
      "damage": 3,
      "armor": 1
    },
    "basic": {
      "level": 2,
      "biography": "<p>Estas diminutas criaturas plateadas con aspecto de insecto tienen un tamaño que oscila entre el submilímetro y los 30 cm [1 pie] de diámetro, y emiten breves pulsos de luz láser de color violeta para detectar y tomar muestras de su entorno. Compuestos de alambres y obleas de silicio orgánico, y autoensamblados o evolucionados en algún laboratorio o nave espacial sin nombre, los parásitos de silicio son alimañas que las estaciones y naves espaciales en funcionamiento han aprendido a odiar. A pesar de tomar medidas para evitar su transferencia, una nave sólo puede enterarse de que tiene parásitos de silicio cuando un enjambre brota de una grieta en el cableado o de una costura en el revestimiento de la cubierta después de haber sido agitado por una maniobra de alta-G o alguna otra perturbación. Si esa perturbación es un combate o alguna otra emergencia extrema, los parásitos de silicio arrojados a la situación lo empeoran todo.<\/p>\n<p><strong>Motivación:<\/strong> Defensa, recolectar materiales electrónicos necesarios para autorreplicarse.<\/p>\n<p><strong>Entorno:<\/strong> Normalmente en naves espaciales y estaciones espaciales en grupos de hasta veinte.<\/p>\n<p><strong>Salud:<\/strong> 6<\/p>\n<p><strong>Daño que inflige: <\/strong>3 puntos<\/p>\n<p><strong>Armadura:<\/strong> 1<\/p>\n<p><strong>Movimiento:<\/strong> Corto; sube una distancia corta cada ronda<\/p>\n<p><strong>Ajustes:<\/strong> Nivel 4 para Defensa por Velocidad debido al tamaño.<\/p>\n<p><strong>Combate:<\/strong> Sólo los parásitos de silicio \"grandes\" son un peligro para la mayoría de las criaturas. Cuando cuatro o más parásitos coordinan sus ataques, trata el ataque como el realizado por una sola criatura de nivel 4 que inflige 5 puntos de daño, y con una tirada fallida de Defensa por Vigor de dificultad 4, un ataque que retiene al objetivo hasta que pueda escapar con éxito. Un objetivo retenido recibe automáticamente 5 puntos de daño cada ronda, o incluso más si se acumulan otros parásitos de silicio en la zona. Los parásitos de silicio pueden operar en el vacío completo sin sufrir daños.<\/p>\n<p><strong>Interacción:<\/strong> En general, los parásitos de silicio se comportan como insectos sociales, aunque algunos afirman que un gran número de ellos han actuado con mayor inteligencia y previsión de lo que los simples insectos irreflexivos pueden conseguir.<\/p>\n<p><strong>Uso: <\/strong>Un enjambre de parásitos de silicio inunda la bodega y se hace con un artefacto importante, arrastrándolo por las grietas y paredes de la nave espacial o estación.<\/p>\n<p><strong>Botín: <\/strong>Los nidos de enjambre a menudo contienen algunos Cyphers manifiestos valiosos o piezas de equipo que funcionan.<\/p>\n<p><strong>Intromisiones del DJ:<\/strong> El parásito de silicio dispara su láser sensorial directamente a los ojos del personaje, cegándolo hasta que tenga éxito en una tirada basada en el Vigor de dificultad 4 como su acción.<\/p>"
    },
    "version": 2
  },
  "folder": null,
  "ownership": {
    "default": 0,
    "yThCrv1jSfPXOC2U": 3
  },
  "name": "Parásito de silicio",
  "_id": "r6w6T9wXYqlk7zZE",
  "items": []
}