{
  "img": "systems/cyphersystem/icons/items/artifact.svg",
  "effects": [],
  "system": {
    "archived": false,
    "settings": {
      "general": {
        "nameUnidentified": ""
      }
    },
    "rollButton": {
      "stepModifier": "eased",
      "damage": 0,
      "damagePerLOE": 3,
      "bonus": 0,
      "pool": "Pool",
      "teen": "",
      "additionalSteps": 0,
      "effort1": 0,
      "effort3": 0,
      "assets": 0,
      "effort2": 0,
      "skill": "Practiced",
      "additionalCost": 0
    },
    "description": "<p><strong>Nivel:</strong> 1d6 + 1</p>\n<p><strong>Aspecto:</strong> Guante transparente muy fino con marcas tenues</p>\n<p><strong>Efecto:</strong> Cuando el portador activa el guante (lo que puede requerir pronunciar una palabra de comando o trazar un patrón específico en su superficie), segrega una pequeña cantidad de veneno. La siguiente criatura a la que el portador toque con el guante sufre daño por Velocidad igual al nivel del artefacto (ignora Armadura) y debe hacer una nueva tirada de Defensa por Vigor cada ronda o sufrir de nuevo el daño hasta que tenga éxito en la tirada de defensa o pasen cinco rondas, lo que ocurra primero.</p>\n<p><strong>Agotamiento:</strong> 1 en 1d10</p>",
    "basic": {
      "depletion": "1 in [[/r 1d10 # Depletion roll]]",
      "identified": true,
      "level": "1d6+1"
    },
    "version": 2
  },
  "folder": null,
  "ownership": {
    "default": 0,
    "yThCrv1jSfPXOC2U": 3
  },
  "_stats": {
    "modifiedTime": 1676451419026,
    "systemId": "cyphersystem",
    "lastModifiedBy": "yThCrv1jSfPXOC2U",
    "createdTime": 1676367597896,
    "systemVersion": "2.3.0",
    "coreVersion": "10.291"
  },
  "name": "Toque del envenenador",
  "flags": {
    "core": {
      "sourceId": "Compendium.cyphersystem-compendium.artifacts-fantasy.elLk9SypW5JP57bB"
    }
  },
  "sort": 0,
  "_id": "2xelcmhAyXFhVnCB",
  "type": "artifact",
  "_key": "!items!2xelcmhAyXFhVnCB"
}