{
  "name": "Paquete de aventurero",
  "type": "equipment",
  "img": "systems/cyphersystem/icons/items/equipment.svg",
  "system": {
    "version": 2,
    "description": "<p> Incluye 15 m [50 pies] de cuerda, raciones para tres días, tres púas, un martillo pequeño, un conjunto de ropa de abrigo, botas y tres antorchas.</p>",
    "archived": false,
    "basic": {
      "level": null,
      "quantity": 1
    }
  },
  "effects": [],
  "ownership": {
    "default": 0,
    "yThCrv1jSfPXOC2U": 3
  },
  "flags": {
    "core": {
      "sourceId": "Item.2utoHNu85viUr89d"
    }
  },
  "_stats": {
    "systemId": "cyphersystem",
    "systemVersion": "2.3.0",
    "coreVersion": "10.291",
    "createdTime": 1676109720063,
    "modifiedTime": 1676109839150,
    "lastModifiedBy": "yThCrv1jSfPXOC2U"
  },
  "folder": null,
  "sort": 0,
  "_id": "otKOcNgf85MoPzbM",
  "_key": "!items!otKOcNgf85MoPzbM"
}