{
  "img": "systems/cyphersystem/icons/items/artifact.svg",
  "effects": [],
  "system": {
    "archived": false,
    "settings": {
      "general": {
        "nameUnidentified": ""
      }
    },
    "description": "<p><strong>Nivel:</strong> 1d6 + 1</p>\n<p><strong>Aspecto:</strong> Varilla metálica de 1 m [4 pies] de material desconocido</p>\n<p><strong>Efecto:</strong> Cuando se toca a un objetivo vivo (posiblemente como ataque), la vara inyecta un potente cóctel de biomoléculas artificiales, paralizando al objetivo durante un minuto. El portador de la vara también puede elegir uno de los siguientes efectos adicionales, si se establece antes de atacar.</p>\n<ul>\n <li><p><strong>Agresión:</strong> Las tendencias agresivas del objetivo aumentan durante una hora, durante la cual el objetivo ataca a casi todo lo que encuentra.</p></li>\n <li><p><strong>Calma:</strong> Las tendencias agresivas del objetivo se atenúan durante una hora, durante la cual el objetivo responde a los ataques pero nunca los inicia.</p></li>\n <li><p><strong>Hibernación:</strong> El objetivo entra en hibernación, un sueño similar al coma en el que su metabolismo se ralentiza. Puede pasar meses sin comer ni beber y con una fracción del aire que necesitaría normalmente. Los sonidos fuertes, el daño, los pinchazos persistentes y similares despiertan a alguien en hibernación.</p></li>\n</ul>\n<p><strong>Agotamiento:</strong> 1 en 1d20</p>",
    "basic": {
      "depletion": "1 in [[/r d20]]",
      "identified": true,
      "level": "1d6+1"
    },
    "version": 2
  },
  "folder": null,
  "ownership": {
    "default": 0,
    "yThCrv1jSfPXOC2U": 3
  },
  "_stats": {
    "modifiedTime": 1676818571515,
    "systemId": "cyphersystem",
    "lastModifiedBy": "yThCrv1jSfPXOC2U",
    "createdTime": 1676817955486,
    "systemVersion": "2.3.0",
    "coreVersion": "10.291"
  },
  "name": "Producto Metabólico",
  "flags": {},
  "_id": "CV62n0rF5QZ7Ev6o",
  "sort": 0,
  "type": "artifact",
  "_key": "!items!CV62n0rF5QZ7Ev6o"
}