{
  "img": "systems/cyphersystem/icons/items/ability.svg",
  "effects": [],
  "folder": null,
  "system": {
    "archived": false,
    "settings": {
      "general": {
        "spellTier": "low",
        "sorting": "Ability",
        "unmaskedForm": "Mask"
      },
      "rollButton": {
        "stepModifier": "eased",
        "damage": 0,
        "damagePerLOE": 3,
        "bonus": 0,
        "pool": "Pool",
        "teen": "",
        "additionalSteps": 0,
        "effort1": 0,
        "effort3": 0,
        "assets": 0,
        "effort2": 0,
        "skill": "Practiced",
        "additionalCost": 0
      }
    },
    "description": "<p>Tienes ojo para la disciplina de grupo y la jerarquía, incluso entre tus enemigos. Si un grupo de enemigos está obteniendo algún beneficio por trabajar juntos, puedes intentar interrumpir ese beneficio señalando el punto débil de la línea, la formación o el ataque grupal del enemigo. Este efecto dura hasta un minuto o hasta que todos los enemigos afectados pasen una ronda evaluándose y restableciéndose para recuperar su estado normal. Acción para iniciar.<\/p>",
    "basic": {
      "cost": "4",
      "pool": "Intellect"
    },
    "version": 2
  },
  "ownership": {
    "default": 0,
    "k2TkElLx959B0lm5": 3
  },
  "_stats": {
    "modifiedTime": 1664959714394,
    "systemId": "cyphersystem",
    "lastModifiedBy": "rLeavHPrdkq6xjNt",
    "createdTime": null,
    "systemVersion": "2.0.0-a1",
    "coreVersion": "10.286"
  },
  "name": "Romper la línea",
  "flags": {"core": {"sourceId": "Compendium.cyphersystem-compendium.abilities.nJlhmzrhmXvM3QvU"}},
  "_id": "nJlhmzrhmXvM3QvU",
  "sort": 0,
  "type": "ability",
  "_key": "!items!nJlhmzrhmXvM3QvU"
}