{
  "img": "systems/cyphersystem/icons/items/ability.svg",
  "effects": [],
  "system": {
    "archived": false,
    "settings": {
      "general": {
        "spellTier": "low",
        "sorting": "Ability",
        "unmaskedForm": "Mask"
      },
      "rollButton": {
        "stepModifier": "eased",
        "damage": 0,
        "damagePerLOE": 3,
        "bonus": 0,
        "pool": "Pool",
        "teen": "",
        "additionalSteps": 0,
        "effort1": "0",
        "effort3": "0",
        "assets": "0",
        "effort2": "0",
        "skill": "Practiced",
        "additionalCost": 0
      }
    },
    "description": "<p>Elige tu Reserva de Vigor o tu Reserva de Velocidad. Cuando gastes puntos para activar tus capacidades de rasgo, puedes gastar puntos de esta Reserva en lugar de tu Reserva de Intelecto (en cuyo caso utilizas tu Ventaja de Vigor o tu Ventaja de Velocidad en lugar de tu Ventaja de Intelecto, según corresponda). Capacitador</p>",
    "basic": {
      "cost": "0",
      "pool": "Pool"
    },
    "version": 2
  },
  "folder": null,
  "ownership": {
    "default": 0,
    "yThCrv1jSfPXOC2U": 3
  },
  "_stats": {
    "modifiedTime": 1676106203364,
    "systemId": "cyphersystem",
    "lastModifiedBy": "yThCrv1jSfPXOC2U",
    "createdTime": 1676106188467,
    "systemVersion": "2.3.0",
    "coreVersion": "10.291"
  },
  "name": "Poder innato",
  "flags": {
    "core": {
      "sourceId": "Item.7Pu2bn67iFPxXXPh"
    }
  },
  "sort": 0,
  "_id": "95judMTwajJoxNfy",
  "type": "ability",
  "_key": "!items!95judMTwajJoxNfy"
}