{
  "img": "systems/cyphersystem/icons/items/ability.svg",
  "effects": [],
  "folder": null,
  "system": {
    "archived": false,
    "settings": {
      "general": {
        "spellTier": "low",
        "sorting": "Ability",
        "unmaskedForm": "Mask"
      },
      "rollButton": {
        "stepModifier": "eased",
        "damage": "0",
        "damagePerLOE": "3",
        "bonus": "0",
        "pool": "Pool",
        "teen": "",
        "additionalSteps": "0",
        "effort1": "0",
        "effort3": "0",
        "assets": "0",
        "effort2": "0",
        "skill": "Practiced",
        "additionalCost": 0
      }
    },
    "description": "<p>Tú y todos los objetivos que designes dentro del alcance inmediato ganan +5 de Armadura contra un tipo de daño elemental directo (como el fuego, el rayo, las sombras o las espinas) durante una hora, o hasta que vuelvas a lanzar este conjuro. Cada nivel de Esfuerzo aplicado aumenta la protección elemental en +2. Acción para iniciar.</p>",
    "basic": {
      "cost": "4+",
      "pool": "Intellect"
    },
    "version": 2
  },
  "ownership": {
    "default": 0,
    "k2TkElLx959B0lm5": 3
  },
  "_stats": {
    "modifiedTime": 1664959717016,
    "systemId": "cyphersystem",
    "lastModifiedBy": "rLeavHPrdkq6xjNt",
    "createdTime": null,
    "systemVersion": "2.0.0-a1",
    "coreVersion": "10.286"
  },
  "name": "Protección elemental",
  "flags": {
    "core": {
      "sourceId": "Compendium.cyphersystem-compendium.abilities.XR8WeRW3OlbCIjlJ"
    }
  },
  "_id": "XR8WeRW3OlbCIjlJ",
  "sort": 0,
  "type": "ability",
  "_key": "!items!XR8WeRW3OlbCIjlJ"
}